text_to_font/__init__.py
text_to_font/transformations.py
text_to_font-0.1.1.dist-info/LICENSE
text_to_font-0.1.1.dist-info/METADATA
text_to_font-0.1.1.dist-info/WHEEL
text_to_font-0.1.1.dist-info/top_level.txt
text_to_font-0.1.1.dist-info/RECORD
