Metadata-Version: 2.1
Name: text-to-font
Version: 0.1.1
Summary: Turns text into ascii art
Home-page: https://github.com/emilkovacev/text-to-font
Author: Emil Kovacev
Author-email: emilkovacev@gmail.com
License: 'MIT'
Project-URL: Bug Tracker, https://github.com/emilkovacev/text-to-font/issues
Platform: UNKNOWN
Classifier: Programming Language :: Python :: 3
Classifier: License :: OSI Approved :: MIT License
Classifier: Operating System :: OS Independent
Requires-Python: >=3.6
License-File: LICENSE
Requires-Dist: Pillow (>=8.0)
